sqlalchemy_wrapper/.DS_Store
sqlalchemy_wrapper/__init__.py
sqlalchemy_wrapper/context.py
sqlalchemy_wrapper/db/__init__.py
sqlalchemy_wrapper/db/operators.py
sqlalchemy_wrapper/db/query.py
sqlalchemy_wrapper/db/settings.py
sqlalchemy_wrapper/exceptions.py
sqlalchemy_wrapper/logger.py
sqlalchemy_wrapper/manager.py
sqlalchemy_wrapper/utils.py
tests/.coveragerc
tests/__init__.py
tests/base_model.py
tests/conftest.py
tests/db/__init__.py
tests/db/test_operators.py
tests/db/test_query.py
tests/db/test_settings.py
tests/models.py
tests/test_context.py
tests/test_manager.py
tests/test_utils.py
sqlalchemy_django_wrapper-0.1.1.dist-info/WHEEL
sqlalchemy_django_wrapper-0.1.1.dist-info/METADATA
sqlalchemy_django_wrapper-0.1.1.dist-info/RECORD
