Metadata-Version: 2.1
Name: sqlalchemy-django-wrapper
Version: 0.1.1
Summary: A wrapper on top of sqlalchemy that allow to make django orm style query
License: GNU GPLv3
Author: Soumaila
Author-email: admin@cloudmali.ml
Requires-Python: >=3.9,<4.0
Classifier: License :: Other/Proprietary License
Classifier: Programming Language :: Python :: 3
Classifier: Programming Language :: Python :: 3.9
Classifier: Programming Language :: Python :: 3.10
Requires-Dist: PyYAML (==6.0)
Requires-Dist: SQLAlchemy (==1.4.41)
Requires-Dist: cfgv (==3.3.1)
Requires-Dist: distlib (==0.3.6)
Requires-Dist: filelock (==3.8.0)
Requires-Dist: greenlet (==1.1.3)
Requires-Dist: identify (==2.5.5)
Requires-Dist: jsonformatter (==0.3.1)
Requires-Dist: nodeenv (==1.7.0)
Requires-Dist: platformdirs (==2.5.2)
Requires-Dist: psycopg2 (==2.9.3)
Requires-Dist: pydantic (==1.10.2)
Requires-Dist: toml (==0.10.2)
Requires-Dist: typing-extensions (==4.3.0)
